<?xml version="1.0" encoding="UTF-8"?>
<!DOCTYPE hibernate-mapping PUBLIC
        "-//Hibernate/Hibernate Mapping DTD 3.0//EN"
        "http://www.hibernate.org/dtd/hibernate-mapping-3.0.dtd">

<hibernate-mapping>
    <class name="org.emsi.entities.TaxonPath" table="lom_taxon_path">
        <id name="id" column="id" type="java.lang.Long">
            <generator class="identity"/>
        </id>
        
        <property name="source" column="source" type="string" length="500"/>
        
        <!-- Relation vers Classification -->
        <many-to-one name="classification" class="org.emsi.entities.Classification" column="classification_id"/>
        
        <!-- Taxons -->
        <set name="taxons" inverse="true" cascade="all-delete-orphan">
            <key column="taxon_path_id"/>
            <one-to-many class="org.emsi.entities.Taxon"/>
        </set>
    </class>
</hibernate-mapping>
